.gitignore
LICENSE.txt
README.md
pyproject.toml
requirements.txt
setup.py
tox.ini
integration_tests/__init__.py
integration_tests/run.py
kaistack/__init__.py
kaistack.egg-info/PKG-INFO
kaistack.egg-info/SOURCES.txt
kaistack.egg-info/dependency_links.txt
kaistack.egg-info/entry_points.txt
kaistack.egg-info/requires.txt
kaistack.egg-info/top_level.txt
kaistack/auth/__init__.py
kaistack/auth/exceptions.py
kaistack/auth/token.py
kaistack/cli/__init__.py
kaistack/cli/cli.py
kaistack/clients/__init__.py
kaistack/clients/grpcclient/__init__.py
kaistack/clients/grpcclient/pipelinecomponentapis_pb2.py
kaistack/clients/grpcclient/pipelinecomponentapis_pb2_grpc.py
kaistack/clients/openapi_clients/__init__.py
kaistack/clients/openapi_clients/api_client.py
kaistack/clients/openapi_clients/cluster_README.md
kaistack/clients/openapi_clients/configuration.py
kaistack/clients/openapi_clients/exceptions.py
kaistack/clients/openapi_clients/pipelinecomponents_README.md
kaistack/clients/openapi_clients/rest.py
kaistack/clients/openapi_clients/workflow_README.md
kaistack/clients/openapi_clients/api/__init__.py
kaistack/clients/openapi_clients/api/pipeline_component_service_api.py
kaistack/clients/openapi_clients/api/workflow_service_api.py
kaistack/clients/openapi_clients/cluster/__init__.py
kaistack/clients/openapi_clients/cluster/api_client.py
kaistack/clients/openapi_clients/cluster/configuration.py
kaistack/clients/openapi_clients/cluster/exceptions.py
kaistack/clients/openapi_clients/cluster/rest.py
kaistack/clients/openapi_clients/cluster/api/__init__.py
kaistack/clients/openapi_clients/cluster/api/cluster_service_api.py
kaistack/clients/openapi_clients/cluster/docs/ClusterServiceApi.md
kaistack/clients/openapi_clients/cluster/docs/CodegenArtifactsStoreConfig.md
kaistack/clients/openapi_clients/cluster/docs/CodegenClusterConfig.md
kaistack/clients/openapi_clients/cluster/docs/CodegenGetClusterConfigResponse.md
kaistack/clients/openapi_clients/cluster/docs/CodegenGetNodesResponse.md
kaistack/clients/openapi_clients/cluster/docs/CodegenGetSystemComponentResponse.md
kaistack/clients/openapi_clients/cluster/docs/CodegenGetSystemStatusResponse.md
